Workbook

Sheet Dashboard
A1: Key Metrics
A2: Total Revenue (Yr1) | B2: ='3-Year Forecast'!B2 -> 350000
A3: Total Expenses (Yr1) | B3: ='3-Year Forecast'!B5 -> 21601
A4: Net Profit (Yr1) | B4: ='3-Year Forecast'!B10 -> 90719.2
A5: Gross Margin (Yr1) | B5: ='Financial Ratios'!B2 -> 0.4
A6: Net Profit Margin (Yr1) | B6: ='Financial Ratios'!B4 -> 0.25919771
A7: Revenue Growth (Yr2) | B7: ='Financial Ratios'!C7 -> 0.5
A8: Net Profit Growth (Yr2) | B8: ='Financial Ratios'!C8 -> 0.75591451

Sheet Cost Analysis
A1: Cost Category | B1: Monthly Cost | C1: Annual Cost
A2: Salaries | B2: 12000 | C2: =B2*12 -> 144000
A3: Rent | B3: 3000 | C3: =B3*12 -> 36000
A4: Utilities | B4: 800 | C4: =B4*12 -> 9600
A5: Marketing | B5: 3000 | C5: =B5*12 -> 36000
A6: Office Supplies | B6: 401 | C6: =B6*12 -> 4812
A7: Insurance | B7: 600 | C7: =B7*12 -> 7200
A8: Travel | B8: 500 | C8: =B8*12 -> 6000
A9: IT Services | B9: 700 | C9: =B9*12 -> 8400
A10: Legal & Accounting | B10: 350 | C10: =B10*12 -> 4200
A11: Miscellaneous | B11: 250 | C11: =B11*12 -> 3000
A12: Total | B12: =SUM(B2:B11) -> 21601 | C12: =SUM(C2:C11) -> 259212

Sheet P&L Statement
A1: Item | B1: Amount
A2: Revenue | B2: 350000
A3: Cost of Goods Sold | B3: =B2*0.4 -> 140000
A4: Gross Profit | B4: =B2-B3 -> 210000
A5: Operating Expenses | B5: ='Cost Analysis'!B2 -> 12000
A6: Salaries | B6: ='Cost Analysis'!B3 -> 3000
A7: Rent | B7: ='Cost Analysis'!B4 -> 800
A8: Utilities | B8: ='Cost Analysis'!B5 -> 3000
A9: Marketing | B9: ='Cost Analysis'!B6 -> 401
A10: Office Supplies | B10: ='Cost Analysis'!B7 -> 600
A11: Insurance | B11: ='Cost Analysis'!B8 -> 500
A12: Travel | B12: ='Cost Analysis'!B9 -> 700
A13: IT Services | B13: ='Cost Analysis'!B10 -> 350
A14: Legal & Accounting | B14: ='Cost Analysis'!B11 -> 250
A15: Miscellaneous | B15: =SUM(B5:B14) -> 21601
A16: Total Operating Expenses | B16: =B4-B15 -> 188399
A17: Operating Profit | B17: 5000
A18: Interest Expense | B18: =B16-B17 -> 183399
A19: Net Profit Before Tax | B19: =B18*0.2 -> 36679.8
A20: Income Tax (20%) | B20: =B18-B19 -> 146719.2
A21: Net Profit After Tax

Sheet Financial Ratios
A1: Ratio | B1: Year 1 | C1: Year 2 | D1: Year 3
A2: Gross Margin | B2: ='3-Year Forecast'!B4/'3-Year Forecast'!B2 -> 0.4 | C2: ='3-Year Forecast'!C4/'3-Year Forecast'!C2 -> 0.6 | D2: ='3-Year Forecast'!D4/'3-Year Forecast'!D2 -> 0.6
A3: Operating Margin | B3: ='3-Year Forecast'!B6/'3-Year Forecast'!B2 -> 0.33828286 | C3: ='3-Year Forecast'!C6/'3-Year Forecast'!C2 -> 0.53999722 | D3: ='3-Year Forecast'!D6/'3-Year Forecast'!D2 -> 0.54166397
A4: Net Profit Margin | B4: ='3-Year Forecast'!B10/'3-Year Forecast'!B2 -> 0.25919771 | C4: ='3-Year Forecast'!C10/'3-Year Forecast'!C2 -> 0.42141577 | D4: ='3-Year Forecast'!D10/'3-Year Forecast'!D2 -> 0.42353301
A5: Expense Ratio | B5: ='3-Year Forecast'!B5/'3-Year Forecast'!B2 -> 0.061717143 | C5: ='3-Year Forecast'!C5/'3-Year Forecast'!C2 -> 0.060002778 | D5: ='3-Year Forecast'!D5/'3-Year Forecast'!D2 -> 0.058336034
A6: COGS Ratio | B6: ='3-Year Forecast'!B3/'3-Year Forecast'!B2 -> 0.6 | C6: ='3-Year Forecast'!C3/'3-Year Forecast'!C2 -> 0.4 | D6: ='3-Year Forecast'!D3/'3-Year Forecast'!D2 -> 0.4
A7: Revenue Growth | C7: =(C2-B2)/B2 -> 0.5 | D7: =(D2-C2)/C2 -> 0
A8: Net Profit Growth | C8: =('3-Year Forecast'!C10-'3-Year Forecast'!B10)/'3-Year Forecast'!B10 -> 0.75591451 | D8: =('3-Year Forecast'!D10-'3-Year Forecast'!C10)/'3-Year Forecast'!C10 -> 0.085426061

Sheet 3-Year Forecast
A1: Item | B1: Year 1 | C1: Year 2 | D1: Year 3
A2: Revenue | B2: 350000 | C2: =B2*1.08 -> 378000 | D2: =C2*1.08 -> 408240
A3: Cost of Goods Sold | B3: =B2*0.6 -> 210000 | C3: =C2*0.4 -> 151200 | D3: =D2*0.4 -> 163296
A4: Gross Profit | B4: =B2-B3 -> 140000 | C4: =C2-C3 -> 226800 | D4: =D2-D3 -> 244944
A5: Operating Expenses | B5: ='P&L Statement'!B15 -> 21601 | C5: =B5*1.05 -> 22681.05 | D5: =C5*1.05 -> 23815.103
A6: Operating Profit | B6: =B4-B5 -> 118399 | C6: =C4-C5 -> 204118.95 | D6: =D4-D5 -> 221128.9
A7: Interest Expense | B7: 5000 | C7: 5000 | D7: 5000
A8: Net Profit Before Tax | B8: =B6-B7 -> 113399 | C8: =C6-C7 -> 199118.95 | D8: =D6-D7 -> 216128.9
A9: Income Tax (20%) | B9: =B8*0.2 -> 22679.8 | C9: =C8*0.2 -> 39823.79 | D9: =D8*0.2 -> 43225.78
A10: Net Profit After Tax | B10: =B8-B9 -> 90719.2 | C10: =C8-C9 -> 159295.16 | D10: =D8-D9 -> 172903.12
